pyjab/__init__.py
pyjab/accessibleinfo.py
pyjab/config.py
pyjab/jabdriver.py
pyjab/jabelement.py
pyjab/jabfixedfunc.py
pyjab/common/__init__.py
pyjab/common/actorscheduler.py
pyjab/common/by.py
pyjab/common/exceptions.py
pyjab/common/logger.py
pyjab/common/role.py
pyjab/common/service.py
pyjab/common/shortcutkeys.py
pyjab/common/singleton.py
pyjab/common/states.py
pyjab/common/textreader.py
pyjab/common/types.py
pyjab/common/win32utils.py
pyjab/common/xpathparser.py
pyjab-1.1.7.dist-info/LICENSE
pyjab-1.1.7.dist-info/METADATA
pyjab-1.1.7.dist-info/WHEEL
pyjab-1.1.7.dist-info/top_level.txt
pyjab-1.1.7.dist-info/RECORD
