Metadata-Version: 2.1
Name: pyjab
Version: 1.1.7
Summary: Python implementation for Java application UI automation with Java Access Bridge
Home-page: https://github.com/gaozhao1989/pyjab
Author: Gary Gao
Author-email: gaozhao89@qq.com
License: GPLv2
Platform: UNKNOWN
Classifier: License :: OSI Approved :: GNU General Public License v2 (GPLv2)
Classifier: Intended Audience :: Developers
Classifier: Programming Language :: Python
Classifier: Programming Language :: Python :: 3.8
Classifier: Development Status :: 5 - Production/Stable
Classifier: Operating System :: Microsoft :: Windows
Classifier: Topic :: Software Development :: Libraries :: Java Libraries
Classifier: Topic :: Home Automation
Classifier: Topic :: Utilities
Requires-Python: >=3.8
License-File: LICENSE
Requires-Dist: Pillow (>=8.3.2)
Requires-Dist: pypiwin32 (>=223)
Requires-Dist: pywin32 (>=302)
